{"data":[{"en":"fracture","zh":"n. 裂缝( 痕); 骨折 v.(使)断裂,( 使) 折断"},{"en":"fragile","zh":"a. 易碎的，脆的，易损坏的；虚弱的，脆弱的"},{"en":"fragment","zh":"n. 碎片, 小部分,片断"},{"en":"fragrant","zh":"a. 香的; 芬芳的"},{"en":"frame","zh":"n. 框架; 体格;骨架; 组织;机构 v. 设计;制定"},{"en":"framework","zh":"n. 构架; 框架;结构; 组织;机构"},{"en":"frank","zh":"a. 坦白的, 直率的"},{"en":"fraud","zh":"n. 欺诈，诈骗；欺骗( 行为)；骗子；假货"},{"en":"free","zh":"a. 自由的; 免费的;免税的; 空闲的 vt.释放"},{"en":"freedom","zh":"n. 自由, 自主,免除, 特权"},{"en":"freeze","zh":"v. 使结冰, 使凝固"},{"en":"freight","zh":"n. 货物, 货运,运费"},{"en":"frequency","zh":"n. 频率, 周率"},{"en":"frequent","zh":"a. 时常发生的, 频繁的"},{"en":"fresh","zh":"a. 新鲜的, 无经验的"},{"en":"friction","zh":"n. 磨擦, 摩擦力"},{"en":"Friday","zh":"n. 星期五"},{"en":"fridge","zh":"n.(refrigerator 的略语)冰箱"},{"en":"friend","zh":"n. 朋友"},{"en":"friendly","zh":"a. 友好的, 友谊的"},{"en":"friendship","zh":"n. 友谊, 友好"},{"en":"fright","zh":"n. 恐怖"},{"en":"frighten","zh":"v. 使惊恐"},{"en":"fringe","zh":"n. 边缘；( 窗帘)缘饰；额前垂发 vt .饰…的边"},{"en":"frog","zh":"n. 蛙"},{"en":"from","zh":"prep.从，自从；由于；离；根据，按；去除"},{"en":"front","zh":"a. 前面的, 前部的 n. 正面; 前线,战线 v. 面对"},{"en":"frontier","zh":"n. 国境, 边境;尖端, 新领域"},{"en":"frost","zh":"n. 霜, 霜冻,严寒"},{"en":"frown","zh":"v. 皱眉"},{"en":"fruit","zh":"n. 水果, 果实;成果, 效果"},{"en":"fruitful","zh":"a. 多产的; 果实累累的,富有成效的"},{"en":"frustrate","zh":"vt.挫败,阻挠, 使灰心"},{"en":"fry","zh":"v. 油煎, 油炸"},{"en":"fuel","zh":"n. 燃料 vt .给…加燃料"},{"en":"fulfill","zh":"v.(fulfil)完成, 履行,实践, 满足"},{"en":"full","zh":"a.(of)满的, 充满的 a./ad.完全, 充分"},{"en":"fume","zh":"n.(浓烈或难闻的）烟，气，汽"},{"en":"fun","zh":"n. 玩笑, 娱乐;有趣的人( 或事物)"},{"en":"function","zh":"n. 功能, 作用;(pl.)职务;函数 v. 起作用"},{"en":"fund","zh":"n. 资金, 基金;存款, 现款;( 知识等的)累积"},{"en":"fundamental","zh":"a. 基础的, 基本的 n.(pl.)基本原则,基本原理"},{"en":"funeral","zh":"n. 丧葬, 葬礼"},{"en":"funny","zh":"a. 滑稽的, 可笑的"},{"en":"fur","zh":"n. 毛, 毛皮"},{"en":"furious","zh":"a. 狂怒的, 狂暴的,猛烈的"},{"en":"furnace","zh":"n. 炉子, 熔炉"},{"en":"furnish","zh":"v. 供应, 提供;装备, 布置"},{"en":"furniture","zh":"n. 家具"},{"en":"further","zh":"ad./a.更远, 更往前;进一步 v. 促进,增进"},{"en":"furthermore","zh":"ad.而且,此外"},{"en":"fuse","zh":"n. 保险丝, 导火线,引信 v. 熔化,熔合"},{"en":"fuss","zh":"n./v.忙乱,大惊小怪"},{"en":"futile","zh":"a. 无效的，无用的，无希望的"},{"en":"future","zh":"n. 将来, 未来;前途, 前景 a. 将来的, 未来的"},{"en":"gain","zh":"v. 获得；增加；表等走快 n. 增进,增加；收益"},{"en":"galaxy","zh":"n. 星系;(the Galaxy)银河( 系); 一群显赫的人"},{"en":"gallery","zh":"n. 长廊,画廊, 美术馆"},{"en":"gallon","zh":"n. 加仑"},{"en":"gallop","zh":"v./n.奔驰, 飞奔"},{"en":"gamble","zh":"n./v.投机, 冒险;赌博"},{"en":"game","zh":"n. 游戏，娱乐；比赛；(pl.)运动会 vi .赌博"},{"en":"gang","zh":"n. 一帮,一群, 一伙"},{"en":"gaol","zh":"n.(jail)监狱；(不加冠词) 监禁 vt.使…坐牢"},{"en":"gap","zh":"n. 缺口;差距; 空白;缺乏"},{"en":"garage","zh":"n. 车库,飞机库; 修车厂"},{"en":"garbage","zh":"n. 垃圾"},{"en":"garden","zh":"n.(菜, 花)园; 公园"},{"en":"garlic","zh":"n. 蒜，大蒜粉"},{"en":"garment","zh":"n.(一件) 衣服"},{"en":"gas","zh":"n. 气体；煤气；汽油；毒气 vt.毒(死) ；加油"},{"en":"gasoline","zh":"n.(gasolene)汽油"},{"en":"gasp","zh":"n. 喘息,气喘 v. 喘息;气吁吁地说"},{"en":"gate","zh":"n. 大门；入口；观众人数，门票收入"},{"en":"gather","zh":"v. 聚集,聚拢; 推测,推断"},{"en":"gauge","zh":"n. 标准尺寸;规格; 量规,量表 v. 测量"},{"en":"gay","zh":"a. 快乐的,愉快的, 色彩鲜艳的 n. 同性恋"},{"en":"gaze","zh":"v./n.凝视, 注视"},{"en":"gear","zh":"n. 齿轮,传动装置 v.(to)调整,使适合"},{"en":"gender","zh":"n.(生理上的) 性；(名词、代词等的) 性"},{"en":"gene","zh":"n. 基因"},{"en":"general","zh":"a. 一般的,普通的; 总的,大体的 n. 将军"},{"en":"generalize","zh":"v.(generalise)归纳,概括; 推广,普及"},{"en":"generate","zh":"vt .产生, 发生;生殖"},{"en":"generation","zh":"n. 产生,发生; 一代(人)"},{"en":"generator","zh":"n. 发电机,发生器"},{"en":"generous","zh":"a. 宽宏大量的,慷慨的"},{"en":"genetic","zh":"a. 遗传(学) 的 n.[-s]遗传学"},{"en":"genius","zh":"n. 天才"},{"en":"gentle","zh":"a. 和蔼的,文雅的, 有礼貌的"},{"en":"gentleman","zh":"n. 绅士,先生"},{"en":"gently","zh":"ad .文雅地, 有礼貌地;轻轻地"},{"en":"genuine","zh":"a. 真正的,名副其实的"},{"en":"geography","zh":"n. 地理(学)"},{"en":"geology","zh":"n. 地质(学)"},{"en":"geometry","zh":"n. 几何(学)"},{"en":"germ","zh":"n. 微生物,细菌"},{"en":"gesture","zh":"n. 姿势,姿态, 手势 v. 做手势"},{"en":"get","zh":"v. 获得，得到；使，使得；变得，成为；到达"},{"en":"ghost","zh":"n. 鬼魂,幽灵"},{"en":"giant","zh":"n. 巨人 a. 巨大的"},{"en":"gift","zh":"n. 礼品,赠品; 天赋,才能"},{"en":"gigantic","zh":"a. 巨大的,庞大的"},{"en":"giggle","zh":"vi .／n. 痴笑；咯咯地笑 vt .咯咯地笑着说"},{"en":"girl","zh":"n. 少女，姑娘，女孩；女职员"},{"en":"give","zh":"v. 给，授予；供给；献出，让步；捐赠；发表"},{"en":"glad","zh":"a. 高兴的，快活的；乐意的，情愿的"},{"en":"glamor","zh":"n.(glamour)魅力; 魔法 vt.迷惑"},{"en":"glance","zh":"v.(at,over)扫视 n. 匆匆看,一瞥, 一眼"},{"en":"glare","zh":"vi .怒目而视; 发射强光 n. 强光; 怒视;炫耀"},{"en":"glass","zh":"n. 玻璃;玻璃杯; 镜子;(pl.)眼镜"},{"en":"glide","zh":"n./v.溜, 滑行;( 时间)消逝"},{"en":"glimpse","zh":"n./v.一瞥, 瞥见"},{"en":"glitter","zh":"n. 光辉,灿烂 v. 闪闪发光;闪耀"},{"en":"global","zh":"a. 球形的;全球的, 全世界的;全面的"},{"en":"globe","zh":"n. 球体,地球仪; 地球,世界"},{"en":"gloomy","zh":"a. 阴暗的,阴沉的, 令人沮丧的,阴郁的"},{"en":"glorious","zh":"a. 壮丽的,辉煌的; 光荣的"},{"en":"glory","zh":"n. 光荣,荣誉"},{"en":"glove","zh":"n. 手套"},{"en":"glow","zh":"v. 发热, 发光,发红 n. 白热"},{"en":"glue","zh":"n. 胶, 胶水 v. 胶合, 粘贴"},{"en":"go","zh":"v. 去，离开；走；放置；变成；运转 n. 围棋"},{"en":"goal","zh":"n. 目的, 目标;守门员, 球门;进球"},{"en":"goat","zh":"n. 山羊"},{"en":"god","zh":"n. 上帝( 小写 god 泛指所有的“神，神像”)"},{"en":"gold","zh":"n. 金，黄金；金币；金黄色 a. 金的，金制的"},{"en":"golden","zh":"a. 金黄色的; 贵重的,极好的"},{"en":"golf","zh":"n. 高尔夫球"},{"en":"good","zh":"a. 好的; 善良的;擅长的; 乖的 n. 好处; 利益"},{"en":"goodby","zh":"int.(goodbye)再见"},{"en":"goodness","zh":"n. 善良，仁慈；( 食物等)精华 int.天哪"},{"en":"goods","zh":"n.(pl.)货物，商品"},{"en":"goose","zh":"n.(pl.geese)鹅, 雌鹅,鹅肉"},{"en":"gorgeous","zh":"a. 华丽的；灿烂的；美丽的；宜人的；棒的"},{"en":"gossip","zh":"n./v.(说) 闲话,闲聊"},{"en":"govern","zh":"v. 统治, 管理;决定, 支配"},{"en":"government","zh":"n. 政府, 内阁;管理, 支配;政治, 政体"},{"en":"governor","zh":"n. 统治者, 管理者,总督, 州(省) 长"},{"en":"gown","zh":"n. 长袍，特殊场合穿的长服"},{"en":"grab","zh":"v./n.(at)抓(住); 夺( 得)"},{"en":"grace","zh":"n. 优美, 文雅;恩惠, 恩泽;宽限, 缓刑;感恩祷告"},{"en":"graceful","zh":"a. 优美的, 文雅的,大方的"},{"en":"gracious","zh":"a. 亲切的, 客气的;宽厚的, 仁慈的"},{"en":"grade","zh":"n. 等级, 级别;年级; 分数 v. 分等, 分级"},{"en":"gradual","zh":"a. 逐渐的, 逐步的"},{"en":"graduate","zh":"n. 大学毕业生, 研究生 v. 大学毕业 a. 毕了业的"},{"en":"grain","zh":"n. 谷物, 谷类;颗粒, 细粒"},{"en":"grammar","zh":"n. 语法, 语法书"},{"en":"gramme","zh":"n.(gram)克"},{"en":"grand","zh":"a. 盛大的, 豪华的;重大的, 主要的"},{"en":"grandmother","zh":"n. 祖母, 外祖母"},{"en":"grant","zh":"v. 同意, 准予;授予 n. 授予物;津贴; 转让证书"},{"en":"grape","zh":"n. 葡萄"},{"en":"graph","zh":"n. 图表, 曲线图"},{"en":"graphic","zh":"a. 绘画似的, 图解的, 生动的"},{"en":"grasp","zh":"v./n.抓住,抓紧; 掌握,领会"},{"en":"grass","zh":"n. 草，草地"},{"en":"grateful","zh":"a.(to,for)感激的; 感谢的"},{"en":"gratitude","zh":"n. 感激, 感谢"},{"en":"grave","zh":"n. 坟墓 a. 严肃的,庄重的"},{"en":"gravity","zh":"n. 重力, 引力;严肃, 庄重"},{"en":"graze","zh":"vi.吃青草 vt.放牧;擦伤; 掠过 .n.擦伤(处)"},{"en":"grease","zh":"n. 动物脂, 油脂,润滑脂 v. 抹油,润滑"},{"en":"great","zh":"a. 伟大的；重要的；大量的；很好的；美好的"},{"en":"greedy","zh":"a. 贪吃的, 贪婪的,渴望的"},{"en":"green","zh":"a. 绿色的; 生的;未成熟的 n. 绿色;蔬菜; 植物"},{"en":"greenhouse","zh":"n. 温室"},{"en":"greet","zh":"v. 致敬, 敬意,迎接; 扑(鼻), 入( 耳), 触(目)"},{"en":"greeting","zh":"n. 问候, 致敬"},{"en":"grey","zh":"n./a.(gray)灰色(的)"},{"en":"grief","zh":"n. 悲伤，悲痛；悲伤的事，悲痛的缘由"},{"en":"grieve","zh":"v. 使悲伤, 使伤心"},{"en":"grim","zh":"a. 严酷的，令人害怕的；不愉快的，讨厌的"},{"en":"grin","zh":"n./vi.露齿而笑，咧嘴一笑"},{"en":"grind","zh":"v. 磨( 碎), 碾(碎)"},{"en":"grip","zh":"v./n.紧握,抓紧; 掌握"},{"en":"groan","zh":"v./n.呻吟"},{"en":"grocer","zh":"n. 食品商, 杂货商"},{"en":"grope","zh":"n./v.摸索,探索"},{"en":"gross","zh":"a. 总的, 毛(重) 的;粗鲁的, 粗俗的 n. 总额"},{"en":"ground","zh":"n. 地，地面，土地；场地，场所；理由，根据"},{"en":"group","zh":"n. 群,组 v. 分组"},{"en":"grow","zh":"v. 生长，成长；渐渐变成；栽培，种植；发展"},{"en":"grown-up","zh":"a. 成长的,成熟的, 成人的 n. 成年人"},{"en":"growth","zh":"n. 生长,增长, 发展"},{"en":"guarantee","zh":"n. 保证,保证书 v. 保证,担保"},{"en":"guard","zh":"v./n.保卫，守卫，提防 n. 哨兵，警卫，看守"},{"en":"guess","zh":"v./n.猜测，推测；以为；猜想[ 同]surmise"},{"en":"guest","zh":"n. 客人,宾客, 旅客"},{"en":"guidance","zh":"n. 引导,指导"},{"en":"guide","zh":"n. 领路人;指南, 导游 v. 领路; 指导;支配; 管理"},{"en":"guideline","zh":"n. 指导方针，指导原则，准则，标准"},{"en":"guilt","zh":"n. 罪过,内疚"},{"en":"guilty","zh":"a.(of)有罪的,内疚的"},{"en":"guitar","zh":"n. 吉他 vi.弹吉他"},{"en":"gulf","zh":"n. 海湾"},{"en":"gum","zh":"n. 树胶;口香糖"},{"en":"gun","zh":"n. 枪，炮，手枪"},{"en":"gut","zh":"n.[pl.]胆量；内脏 a. 本能的 vt .取出内脏"},{"en":"guy","zh":"n. 家伙, 人"},{"en":"gymnasium","zh":"n.(gym)体育馆，健身房"},{"en":"habit","zh":"n. 习惯,习性, 脾性"},{"en":"habitat","zh":"n.(动物的) 栖息地，(植物的) 产地"},{"en":"hail","zh":"v. 下雹;欢呼, 欢迎 n. 雹"},{"en":"hair","zh":"n. 毛发，头发；绒毛，毛状物"},{"en":"half","zh":"n. 半，一半 a. 一半的，不完全的 ad .一半地"},{"en":"hall","zh":"n. 礼堂,会堂, 办公大楼,门厅"},{"en":"halt","zh":"n. 止步,停步, 停止前进 v. 止步,( 使) 停止"},{"en":"ham","zh":"n. 火腿"},{"en":"hamburger","zh":"n. 汉堡包,牛肉饼"},{"en":"hammer","zh":"n. 铁锤,槌, 榔头 v. 锤击, 敲打"},{"en":"hamper","zh":"v. 妨碍,阻碍, 牵制"},{"en":"hand","zh":"n. 手，人手，雇员；专门业人员；指针 v. 交"},{"en":"handbook","zh":"n. 手册,指南"},{"en":"handful","zh":"n. 一把;少数; 一小撮"},{"en":"handicap","zh":"v. 妨碍 n.(身体或智力方面的)缺陷; 不利条件"},{"en":"handkerchief","zh":"n. 手帕"},{"en":"handle","zh":"n. 柄,把手, 拉手 v. 处理, 对待,操纵; 触,抚养"},{"en":"handsome","zh":"a. 漂亮的,英俊的; 慷慨的,数量可观的"},{"en":"handwriting","zh":"n. 笔迹,手迹, 书法"},{"en":"handy","zh":"a. 手边的,近便的; 方便的"},{"en":"hang","zh":"v. 悬挂,垂吊; 吊死,绞死"},{"en":"happen","zh":"v.(偶然) 发生；碰巧，恰好"},{"en":"happy","zh":"a. 快乐的，幸福的；乐意的；令人满意的"},{"en":"harassment","zh":"n. 骚扰，扰乱；烦恼，烦乱"},{"en":"harbor","zh":"n.(harbour)海港; 避难所 v. 隐匿, 窝藏"},{"en":"hard","zh":"a. 坚硬的；结实的；困难的；难忍的；严厉的"},{"en":"harden","zh":"v.(使) 变硬"},{"en":"hardly","zh":"ad .几乎不, 简直不;仅仅"},{"en":"hardship","zh":"n. 艰难,困苦"},{"en":"hardware","zh":"n. 五金,金属制品; 硬件"},{"en":"harm","zh":"n./v.伤害, 损害,危害"},{"en":"harmony","zh":"n. 协调,和谐; 融洽"},{"en":"harness","zh":"v. 治理,利用 n. 马具,挽具"},{"en":"harsh","zh":"a. 粗糙的；(声音) 刺耳的；苛刻的，严酷的"},{"en":"harvest","zh":"n. 收获,收成; 成果,后果 v. 收获,收割"},{"en":"haste","zh":"n. 匆忙,急速; 草率 v. 赶快; 匆忙"},{"en":"hasty","zh":"a. 匆忙的,仓促的; 草率的"},{"en":"hat","zh":"n. 帽子(一般指有边的帽子)"},{"en":"hatch","zh":"v. 孵,孵出; 策划,图谋 n. 舱口,小门"},{"en":"hate","zh":"v. 恨,憎恨; 不愿,不喜欢 n. 恨,憎恶"},{"en":"hatred","zh":"n. 憎恨,憎恶, 怨恨"},{"en":"haul","zh":"v. 拖曳, 拖运,用力拖"},{"en":"have","zh":"v. 有，具有；体会，经受；从事；使；吃，喝"},{"en":"hawk","zh":"n. 鹰, 隼"},{"en":"hay","zh":"n. 干草"},{"en":"hazard","zh":"n. 危险, 冒险,危害 v. 冒险,拼命"},{"en":"he","zh":"pron.他；(不论性别的) 一个人"},{"en":"head","zh":"n. 头；顶部；领导, 首脑 v. 主管；位于.. 顶部"},{"en":"headache","zh":"n. 头痛"},{"en":"heading","zh":"n. 标题"},{"en":"headline","zh":"n. 大字标题, 新闻标题"},{"en":"headmaster","zh":"n. 校长"},{"en":"headquarters","zh":"n. 司令部, 指挥部;总部, 总局"},{"en":"heal","zh":"v. 治愈, 愈合"},{"en":"health","zh":"n. 健康, 健康状况;卫生"},{"en":"healthy","zh":"a. 健康的, 健壮的;有益健康的, 卫生的"},{"en":"heap","zh":"n.(一)堆, 大量,许多 v.(up)堆,堆起"},{"en":"hear","zh":"v. 听见；审讯；(from)收到.. 的信/ 电话;听说"},{"en":"hearing","zh":"n. 听, 倾听;听力; 审讯"},{"en":"heart","zh":"n. 心( 脏)；内心，感情；热忱；中心，要点"},{"en":"heat","zh":"n. 热, 热度;热烈, 激烈 v.(给)加热,( 使) 变热"},{"en":"heave","zh":"v.(用力)举，提，拉；扔；拖；呕吐 n. 举起"},{"en":"heaven","zh":"n. 天, 天空,天堂;(Heaven)上帝,神"},{"en":"heavy","zh":"a. 重的, 重型的;沉重的, 大量的,猛烈的"},{"en":"hedge","zh":"n. 篱笆, 树篱,障碍物 v. 用树篱围住"},{"en":"heel","zh":"n. 脚后跟, 踵,鞋跟"},{"en":"height","zh":"n. 高, 高度;( 常 pl.)高地, 高处"},{"en":"heighten","zh":"v. 提高, 升高"},{"en":"heir","zh":"n. 继承人"},{"en":"helicopter","zh":"n. 直升( 飞)机"},{"en":"hell","zh":"n. 地狱, 阴间;苦境, 极大痛苦"},{"en":"hello","zh":"int.英( 美)喂, 你好(用来打招呼或引起注意)"},{"en":"helmet","zh":"n. 头盔, 钢盔"},{"en":"help","zh":"v. 帮( 援)助；有助于；[ 呼救]救命 n. 帮助(手)"},{"en":"helpful","zh":"a.(to)有帮助的, 有益的,有用的"},{"en":"hemisphere","zh":"n. 半球"},{"en":"hen","zh":"n. 母鸡"},{"en":"hence","zh":"ad.从此,今后; 因此"},{"en":"henceforth","zh":"ad.今后"},{"en":"her","zh":"pron.[she 的宾格] 她；[she 的所有格]她的"},{"en":"herb","zh":"n. 药草，( 调味用的)香草，草本植物"},{"en":"herd","zh":"n. 群, 兽群,牛群 v. 放牧,群集"},{"en":"here","zh":"ad.在(到，向) 这里；这时；在这一点上"},{"en":"heritage","zh":"n. 遗产, 继承物;传统"},{"en":"hero","zh":"n. 英雄，勇士；男主角，男主人公"},{"en":"heroic","zh":"a. 英雄的，英勇的，崇高的"},{"en":"heroin","zh":"n. 海洛因"},{"en":"heroine","zh":"n. 女英雄; 女主角"},{"en":"hers","zh":"pron.[she 的物主代词] 她的(所有物)"},{"en":"herself","zh":"pron.[反身代词] 她自己；她亲自，她本人"},{"en":"hesitate","zh":"v. 犹豫, 踌躇;含糊, 支吾"},{"en":"hi","zh":"interj.(hey)嗨! 喂!"},{"en":"hide","zh":"v. 隐藏, 躲藏;隐瞒 n. 皮革,兽皮"},{"en":"hierarchy","zh":"n. 等级制度；统治集团，领导层"},{"en":"high","zh":"a. 高的，高度的，高级的，高尚的 ad .高高地"},{"en":"highland","zh":"n. 高地,高原"},{"en":"highlight","zh":"v. 使显著, 使突出;强调 n. 最精彩的部分"},{"en":"highly","zh":"ad.高度地,很, 非常;赞许地"},{"en":"highway","zh":"n. 公路, 大路"},{"en":"hijack","zh":"v. 劫持，劫机，拦路抢劫"},{"en":"hike","zh":"n. 徒步旅行；增加 vi .徒步旅行 vt.提高"},{"en":"hill","zh":"n. 小山，山岗，高地；[pl.]丘陵(地带)"},{"en":"him","zh":"pron.他(he 的宾格形式)"},{"en":"himself","zh":"pron.[反身代词] 他自己；他本人"},{"en":"hinder","zh":"v.(from)阻止, 妨碍 a. 后面的"},{"en":"hinge","zh":"n. 合页, 铰链 vi.依…而定"},{"en":"hint","zh":"n. 暗示, 提示,线索 v. 暗示,示意"},{"en":"hip","zh":"n. 臀部，髋；屋脊"},{"en":"hire","zh":"n./v.雇用,租借"},{"en":"his","zh":"pron.[he 的所有格/ 物主代词]他的( 所有物)"},{"en":"historian","zh":"n. 历史学家"},{"en":"historic","zh":"a. 有历史意义的; 历史的"},{"en":"historical","zh":"a. 历史的; 有关历史的"},{"en":"history","zh":"n. 历史, 历史学;来历, 经历"},{"en":"hit","zh":"v. 打, 击;碰撞 n. 击中;成功而风行一时的事物"},{"en":"hitherto","zh":"ad.到目前为止,迄今"},{"en":"hobby","zh":"n. 业余爱好, 嗜好,兴趣"},{"en":"hoist","zh":"v. 举起, 升起,吊起"},{"en":"hold","zh":"v. 拿着; 保有;托住; 举行;继续 n. 握住;船舱"},{"en":"holder","zh":"n. 持有者, 占有者;( 台,架等) 支持物"},{"en":"hole","zh":"n. 洞, 孔"},{"en":"holiday","zh":"n. 假日, 节日,假期, 休假"},{"en":"hollow","zh":"a. 空的, 中空的;空洞的, 空虚的 v. 挖空, 凿空"},{"en":"holy","zh":"a. 神圣的, 圣洁的"},{"en":"home","zh":"ad.回家,在家 n. 家；家乡 a. 家庭的；家乡的"},{"en":"homework","zh":"n.(学生的)家庭作业、课外人员"},{"en":"homogeneous","zh":"a. 同种类的，同性质的，有相同特征的"},{"en":"honest","zh":"a. 诚实的, 正直的,老实的"},{"en":"honey","zh":"n. 蜜, 蜂蜜"},{"en":"honor","zh":"n.(honour)尊敬, 敬意;荣誉, 光荣 v. 尊敬"},{"en":"honorable","zh":"a.(honourable)可敬的; 荣誉的,光荣的"},{"en":"hook","zh":"n. 钩, 吊钩,钩状物 v. 钩住"},{"en":"hop","zh":"v. 人单足跳; 跳上(车等) n. 蹦跳; 短程飞行"},{"en":"hope","zh":"n. 希望，期望；希望的人或事 v. 希望，期望"},{"en":"hopeful","zh":"a. 给人希望的，抱有希望的"},{"en":"horizon","zh":"n. 地平线; 眼界,见识"},{"en":"horizontal","zh":"a. 地平线的; 水平的"},{"en":"horn","zh":"n.(牛羊等的)角; 号,喇叭; 角状物;角制品"},{"en":"horrible","zh":"a. 令人恐惧的，可怕的；极讨厌的，糟透的"},{"en":"horror","zh":"n. 恐怖, 战栗"},{"en":"horse","zh":"n. 马；跳马，鞍马 v. 骑马"},{"en":"horsepower","zh":"n.[机]马力"},{"en":"hose","zh":"n. 水龙带, 软管 v. 用软管( 淋浇,冲洗)"},{"en":"hospital","zh":"n. 医院"},{"en":"hospitality","zh":"n. 好客, 殷勤,款待"},{"en":"host","zh":"n. 主人; 旅店老板;节目主持人; 一大群,许多"},{"en":"hostage","zh":"n. 人质"},{"en":"hostess","zh":"n. 女主人, 女主持人"},{"en":"hostile","zh":"a. 敌对的, 敌方的,敌意的"},{"en":"hot","zh":"a.(炎)热的；辣的；急躁的；激动的；热衷的"},{"en":"hotel","zh":"n. 旅馆"},{"en":"hound","zh":"n. 猎狗；卑鄙的人 vt .用猎狗追，追逐"},{"en":"hour","zh":"n. 小时，钟点；时刻；课时，工作时间"},{"en":"house","zh":"n. 房屋；商业机构；[H-]议院 v. 给...房子住"},{"en":"household","zh":"n. 家庭，家人 a. 家庭(务) 的，家常的"},{"en":"housewife","zh":"n. 家庭主妇"},{"en":"housework","zh":"n. 家务，家事( 不可数)"},{"en":"housing","zh":"n. 住房，住房供给；( 外、阀)壳，防护罩"},{"en":"hover","zh":"vi.(鸟) 盘旋，翱翔，(人) 逗留在附近徘徊"},{"en":"how","zh":"ad.1.(表示方法、手段、状态) 怎样；如何"},{"en":"however","zh":"ad.然而，可是，不过，无论如何 conj.无论"},{"en":"howl","zh":"n. 怒吼，嗥叫 vi .(风等)怒吼，咆哮"},{"en":"huddle","zh":"n./v.拥挤;聚集 v.(因寒冷、害怕而)缩成一团"},{"en":"hug","zh":"v./n.热烈拥抱,紧抱"},{"en":"huge","zh":"a. 巨大的, 庞大的"},{"en":"hum","zh":"v. 哼曲子；发嗡嗡声；忙碌 n. 嗡嗡声，嘈杂声"},{"en":"human","zh":"a. 人的, 人类的 n."},{"en":"humanity","zh":"n. 人类, 人性,人情;(pl.)人文科学"},{"en":"humble","zh":"a. 谦卑的, 恭顺的;地位低下的 v. 降低,贬低"},{"en":"humid","zh":"a. 湿的, 湿气重的"},{"en":"humidity","zh":"n. 湿气, 湿度"},{"en":"humiliate","zh":"v. 使羞辱，使丢脸[ 同]disgrace"},{"en":"humor","zh":"n.(humour)幽默, 诙谐"},{"en":"humorous","zh":"a. 富于幽默感的，幽默的；滑稽的"},{"en":"hundred","zh":"num.百，一百；[pl.]许多 a. 一百的；许多"},{"en":"hunger","zh":"n./v.饥饿;渴望"},{"en":"hungry","zh":"a. 饥饿的, 渴望的"},{"en":"hunt","zh":"v./n.打猎,猎取;(for)搜索; 寻找"},{"en":"hurl","zh":"vt.猛投，力掷；大声叫骂"},{"en":"hurricane","zh":"n. 飓风"},{"en":"hurry","zh":"vi.匆忙 vt.催促;急运( 派) n. 急(匆) 忙"},{"en":"hurt","zh":"n. 伤痛, 伤害 v. 刺痛, 伤害;伤…的感情"},{"en":"husband","zh":"n. 丈夫"},{"en":"hut","zh":"n. 小屋, 棚屋"},{"en":"hydrogen","zh":"n. 氢"},{"en":"hypocrisy","zh":"n. 伪善，虚伪"},{"en":"hypothesis","zh":"n. 假说, 假设,前提"},{"en":"hysterical","zh":"a. 情绪异常激动的, 歇斯底里的"},{"en":"I","zh":"pron.(主格) 我"},{"en":"ice","zh":"n. 冰；冰冻甜食 vt .冰冻，使成冰"},{"en":"ice-cream","zh":"n. 冰淇淋"},{"en":"idea","zh":"n. 想法，念头；概念，观念；意见，主意"},{"en":"ideal","zh":"a. 理想的; 空想的;理想主义的; 唯心的 n. 理想"},{"en":"identical","zh":"a.(to.with)同一的,同样的"},{"en":"identification","zh":"n. 识别, 鉴别;证件; 认同"},{"en":"identify","zh":"v. 识别, 鉴别;(with)把…和…看成一样"},{"en":"identity","zh":"n. 身份; 本体;特征; 同一(性); 一致; 国籍;等式"},{"en":"ideology","zh":"n. 意识形态，( 政治或社会的)思想意识"},{"en":"idiom","zh":"n. 习语; 成语方言;( 艺术等的)风格, 特色"},{"en":"idiot","zh":"n. 白痴；极蠢的人；笨蛋"},{"en":"idle","zh":"a. 空闲的, 闲置的;懒散的 v. 空费,虚度"},{"en":"if","zh":"conj.(用于连接宾语从句) 是否；是不是"},{"en":"ignite","zh":"v. 点火, 引燃"},{"en":"ignorance","zh":"n. 无知, 愚昧;不知道"},{"en":"ignorant","zh":"a. 无知的, 愚昧的;不知道的"},{"en":"ignore","zh":"v. 不理, 不顾,忽视"},{"en":"ill","zh":"a. 有病的；坏的；恶意的 ad .坏地；不利地"},{"en":"illegal","zh":"a. 不合法的, 非法的"},{"en":"illiterate","zh":"a. 文盲的, 未受教育的"},{"en":"illness","zh":"n. 病, 疾病"},{"en":"illuminate","zh":"vt.照亮，照明；用灯光装饰；说明，阐释"},{"en":"illusion","zh":"n. 幻想，错误的观念；错觉，幻觉，假象"},{"en":"illustrate","zh":"v. 举例说明, 阐明;图解, 加插图"},{"en":"illustration","zh":"n. 说明；例证，插图；举例说明"},{"en":"image","zh":"n. 形象，声誉；印象；像；形象的描述，比喻"},{"en":"imaginary","zh":"a. 想象的, 虚构的"},{"en":"imagination","zh":"n. 想象( 力)；空想，幻觉；想象出来的事物"},{"en":"imaginative","zh":"a. 富有想象力的, 爱想象的"},{"en":"imagine","zh":"v. 想象, 设想,料想"},{"en":"imitate","zh":"v. 模仿, 仿效;仿造, 伪造"},{"en":"imitation","zh":"n. 模仿, 仿效;仿制; 仿造品"},{"en":"immediate","zh":"a. 立即的, 即时的;直接的, 最接近的"},{"en":"immense","zh":"a. 广大的, 巨大的;[ 口]极好的"},{"en":"immerse","zh":"v. 使沉浸在; 使浸没"},{"en":"immigrant","zh":"a.(从国外)移来的, 移民的 n. 移民, 侨民"},{"en":"immune","zh":"a. 免疫的, 有免疫力的;有受影响的; 豁免的"},{"en":"impact","zh":"n. 冲击, 碰撞;影响 v. 影响;挤入, 压紧"},{"en":"impair","zh":"v. 损害, 损伤;削弱, 减少"},{"en":"impart","zh":"vt.传授，给予；告知，通知"},{"en":"impatient","zh":"a. 不耐烦的, 急躁的"},{"en":"imperative","zh":"n. 命令; 需要;规则; 祈使语气 a. 强制的;紧急的"},{"en":"imperial","zh":"a. 帝国的，帝王的；( 度量衡)英制的"},{"en":"impetus","zh":"n. 推动( 力), 促进"},{"en":"implement","zh":"n.(pl.)工具,器具 v. 贯彻,实现"},{"en":"implication","zh":"n. 含意，暗示，暗指；牵连"},{"en":"implicit","zh":"a. 含蓄的;(in)固有的;无疑问的; 绝对的"},{"en":"imply","zh":"v. 意指, 含…意思,暗示"},{"en":"import","zh":"v./n.进口,输入,(pl.)进口商品; 要旨,含意"},{"en":"importance","zh":"n. 重要, 重要性"},{"en":"important","zh":"a. 重要的, 重大的;有地位的, 有权力的"},{"en":"impose","zh":"v. 征( 税);(on)把…强加给"},{"en":"impossible","zh":"a. 不可能的；难以忍受的，很难对付的"},{"en":"impress","zh":"v.(on)印, 盖印;留下印象, 引人注目"},{"en":"impression","zh":"n. 印象, 感想;盖印, 压痕"},{"en":"impressive","zh":"a. 给人深刻印象的, 感人的"},{"en":"improve","zh":"v. 改善, 改进,增进; 好转,进步"},{"en":"improvement","zh":"n. 改进, 进步,增进; 改进措施"},{"en":"impulse","zh":"v. 推动 n. 推动;冲动, 刺激"},{"en":"in","zh":"prep.在…里(内，上) ；用…(表示)ad.进，入"},{"en":"incentive","zh":"n. 刺激; 动力;鼓励; 诱因;动机"},{"en":"inch","zh":"n. 英寸"},{"en":"incidence","zh":"n. 影响程度，影响范围；发生率"},{"en":"incident","zh":"n. 事件, 事变"},{"en":"incidentally","zh":"ad.附带地,顺便提及"},{"en":"incline","zh":"v.(使)倾斜;( 使) 倾向于 n. 斜坡, 斜面"},{"en":"include","zh":"v. 包括, 包含,计入"},{"en":"inclusive","zh":"a.(of)包括的, 包含的;范围广的"},{"en":"income","zh":"n. 收入, 收益,所得"},{"en":"incorporate","zh":"v. 合并, 纳入,结合 a. 合并的"},{"en":"increase","zh":"v./n.增加,增长, 增进"},{"en":"increasingly","zh":"ad.不断增加地,日益"},{"en":"incredible","zh":"a. 不可相信的, 惊人的,不可思议的"},{"en":"incur","zh":"v. 招致, 惹起,遭受"},{"en":"indeed","zh":"ad.确实,实在; 真正地,多么"},{"en":"independence","zh":"n. 独立, 自主"},{"en":"independent","zh":"a.(of)独立的, 自主的"},{"en":"index","zh":"n.(pl.indexes,indices)索引 v. 附以索引"},{"en":"indicate","zh":"v. 指出, 指示;表明, 暗示"},{"en":"indication","zh":"n. 指出, 指示;表明, 暗示"},{"en":"indicative","zh":"a.(of)指示的, 暗示的"},{"en":"indifferent","zh":"a. 冷漠的, 不关心的,不积极的"},{"en":"indignant","zh":"a. 愤慨的, 愤慨不平的"},{"en":"indignation","zh":"n. 愤怒, 愤慨"},{"en":"indispensable","zh":"a.(to,for)必不可少的, 必需的"},{"en":"individual","zh":"a. 个人的, 单独的;独特的 n. 个人,个体"},{"en":"indoor","zh":"a. 室内的, 户内的"},{"en":"induce","zh":"v. 引诱, 劝使;引起, 导致;感应"},{"en":"indulge","zh":"v. 放任，纵容，沉溺；使( 自己)纵情享受"},{"en":"industrial","zh":"a. 工业的, 产业的"},{"en":"industrialize","zh":"v.(industrialise)(使) 工业化"},{"en":"industry","zh":"n. 工业, 产业;勤劳, 勤奋"},{"en":"inertia","zh":"n. 不活动, 惰性;惯性"},{"en":"inevitable","zh":"a. 不可避免的, 必然发生的"},{"en":"infant","zh":"n. 婴儿, 幼儿"},{"en":"infect","zh":"vt.传染，感染；影响(思想等)"},{"en":"infectious","zh":"a. 传染的, 传染性的,有感染力的"},{"en":"infer","zh":"v. 推论, 推断"},{"en":"inference","zh":"n. 推论, 推理,推断; 结论"},{"en":"inferior","zh":"a. 下等的, 下级的;劣等的, 差的 n. 下级, 晚辈"},{"en":"infinite","zh":"a. 无限的, 无穷的 n. 无限"},{"en":"inflation","zh":"n. 通货"},{"en":"influence","zh":"n.(on)影响, 感化;势力, 权势 v. 影响, 感化"},{"en":"influential","zh":"a. 有影响的; 有权势的"},{"en":"inform","zh":"v.(of,about)通知, 告诉,报告; 告发,告密"},{"en":"information","zh":"n. 通知, 报告;情报, 资料,消息; 信息"},{"en":"infrared","zh":"a./n.红外线(的)"},{"en":"infrastructure","zh":"n. 基础结构，基础设施"},{"en":"ingenious","zh":"a. 机敏的; 有独创性的;精致的; 精巧制成的"},{"en":"ingredient","zh":"n.(混合物的)组成部分，配料；成份，要素"},{"en":"inhabit","zh":"vt.居住于,存在于; 栖息于"},{"en":"inhabitant","zh":"n. 居民, 住户"},{"en":"inhale","zh":"v. 吸入( 气体等)，吸( 烟)"},{"en":"inherent","zh":"a. 固有的, 内在的,天生的"},{"en":"inherit","zh":"vt.继承(金钱等) ，经遗传而得(性格、特征)"},{"en":"inhibit","zh":"vt.抑制，约束"},{"en":"initial","zh":"a. 最初的, 开头的;词首的 n. 词首大写字母"},{"en":"initiate","zh":"vt.开始，创始，发动；启蒙，使入门；引入"},{"en":"initiative","zh":"a. 创始的, 起始的 n. 第一步, 创始,主动精神"},{"en":"inject","zh":"vt.注射(药液等) ；注入"},{"en":"injure","zh":"v. 损害, 损伤,伤害"},{"en":"injury","zh":"n. 伤害，损害"},{"en":"ink","zh":"n. 墨水，油墨"},{"en":"inland","zh":"a./ad.国内, 内地,内陆"},{"en":"inlet","zh":"n. 水湾, 小湾;进口, 入口"},{"en":"inn","zh":"n. 小旅馆, 客栈"},{"en":"inner","zh":"a. 内部的, 里面的;内心的"},{"en":"innocent","zh":"a.(of)清白的, 无罪的;无害的; 单纯的,无知的"},{"en":"innovation","zh":"n. 改革，革新；新观念，新方法，新发明"},{"en":"innumerable","zh":"a. 无数的, 数不清的"},{"en":"input","zh":"n./v.输入"},{"en":"inquiry","zh":"n.(enquiry)询问,打听, 调查"},{"en":"insect","zh":"n. 昆虫"},{"en":"insert","zh":"v. 插入, 嵌入;登载 n. 插入物"},{"en":"inside","zh":"a. 里面的 ad .在里面 n. 内部 prep.在…里"},{"en":"insight","zh":"n. 洞察力, 见识"},{"en":"insist","zh":"vi.(on)坚持要求,坚决主张, 坚持"},{"en":"inspect","zh":"vt.检查,调查, 视察"},{"en":"inspiration","zh":"n. 灵感; 鼓舞,激励"},{"en":"inspire","zh":"vt.鼓舞,激起; 使产生灵感"},{"en":"install","zh":"vt.(instal)安装,设置, 安置；使就职,任命"},{"en":"installation","zh":"n. 安装, 设置;装置, 设备"},{"en":"installment","zh":"n.(instalment)分期付款；( 连载的)一期"},{"en":"instance","zh":"n. 例子, 事例,例证"},{"en":"instant","zh":"a. 立即的; 紧迫的;( 食品)速溶的 n. 瞬间,时刻"},{"en":"instantaneous","zh":"a. 瞬间的, 即刻的"},{"en":"instead","zh":"ad.代替,顶替"},{"en":"instinct","zh":"n. 本能, 直觉,天性"},{"en":"institute","zh":"n. 学会, 研究所;学院 v. 设立,设置, 制定"},{"en":"institution","zh":"n. 公共机构; 协会;学校; 研究所;制度; 惯例"},{"en":"instruct","zh":"v. 教, 教授;命令, 指示"},{"en":"instruction","zh":"n. 教授; 指导;(pl.)用法说明(书), 操作指南"},{"en":"instrument","zh":"n. 工具, 仪器,器械; 乐器"},{"en":"instrumental","zh":"a. 仪器的; 器械的;乐器的; 起作用的;有帮助的"},{"en":"insulate","zh":"vt.隔离,孤立; 使绝缘,使绝热"},{"en":"insult","zh":"vt./n.侮辱, 凌辱"},{"en":"insurance","zh":"n. 保险, 保险费,保险业"},{"en":"insure","zh":"vt.保险,给…保险; 保证"},{"en":"intact","zh":"a. 完整无缺的, 未经触动的,未受损伤的"},{"en":"integral","zh":"a. 构成整体所必需的; 完整的"},{"en":"integrate","zh":"v.(into,with)(使) 成为一体,( 使)结合在一起"},{"en":"integrity","zh":"n. 正直, 诚实;完整, 完全"},{"en":"intellectual","zh":"n. 知识分子 a. 智力的，理智的，有理解力的"},{"en":"intelligence","zh":"n. 智力, 聪明;理解力; 情报,消息, 报导"},{"en":"intelligent","zh":"a. 聪明的, 明智的,理智的"},{"en":"intelligible","zh":"a. 可理解的，明白易懂的，清楚的"},{"en":"intend","zh":"vt.想要,打算, 企图"},{"en":"intense","zh":"a. 强烈的, 剧烈的;热烈的, 热情的"},{"en":"intensity","zh":"n. 强烈, 剧烈;强度"},{"en":"intensive","zh":"a. 加强的, 集中的,深入细致的, 精耕细作的"},{"en":"intention","zh":"n. 意图, 意向,目的"},{"en":"interact","zh":"v. 互相作用, 互相影响"},{"en":"intercourse","zh":"n. 交流, 交往,交际, 性交"},{"en":"interest","zh":"n.(in)兴趣, 重要性;利益 v.(in)使发生兴趣"},{"en":"interesting","zh":"a. 有趣的, 引人入胜的"},{"en":"interface","zh":"n. 接合部位，分界面 v.(使) 互相联系"},{"en":"interfere","zh":"v.(in)干涉, 干预;(with)妨碍, 打扰"},{"en":"interference","zh":"n.(in)干涉, 干预;(with)妨碍, 打扰"},{"en":"interim","zh":"a. 中间的, 暂时的,临时的 n. 过渡时期,暂定"},{"en":"interior","zh":"a. 内部的, 里面的 n. 内部, 内地"},{"en":"intermediate","zh":"a. 中间的, 居间的;中级的 n. 中间体,媒介物"},{"en":"intermittent","zh":"a. 间歇的, 断断续续的"},{"en":"internal","zh":"a. 内部的, 内的;国内的, 内政的"},{"en":"international","zh":"a. 国际的, 世界(性) 的,跨国的"},{"en":"internet","zh":"n.[the～] 国际互联网，因特网"},{"en":"interpret","zh":"vt.解释,说明; 口译"},{"en":"interrupt","zh":"v. 中断, 遮断,阻碍; 打断(话), 打扰"},{"en":"intersection","zh":"n. 相交，交叉；道路交叉口，十字路口"},{"en":"interval","zh":"n. 间隔, 间歇;( 幕间或工间)休息"},{"en":"intervene","zh":"v.(in)干涉, 干预;插入, 介入"},{"en":"interview","zh":"v./n.接见,会见; 采访;面试"},{"en":"intimate","zh":"a. 亲密的, 密切的 n. 熟友, 熟人"},{"en":"intimidate","zh":"vt.胁迫，威胁(某人做某事)"},{"en":"into","zh":"prep.到...里面，进入；成为( 表示变化)"},{"en":"intricate","zh":"a. 复杂的, 错综的,难以理解的"},{"en":"intrigue","zh":"n. 阴谋 v. 密谋, 私通;激起…的兴趣; 诡计取得"},{"en":"intrinsic","zh":"a.(指价值、性质)固有的，本质的，内在的"},{"en":"introduce","zh":"vt.介绍；引进，传入；提出(议案等)"},{"en":"introduction","zh":"n.(to)介绍; 传入,引进; 导言,导论, 绪论"},{"en":"intrude","zh":"vi.闯入,侵入 vt.把(思想等) 强加于人;强挤入"},{"en":"intuition","zh":"n. 直觉，直观；凭直觉而知的事物"},{"en":"invade","zh":"vt.入侵,侵略, 侵袭,侵扰"},{"en":"invalid","zh":"n. 病人, 伤残人 a. 有病的, 伤残的;无效的"},{"en":"invaluable","zh":"a. 非常宝贵的, 无价的"},{"en":"invariably","zh":"ad.不变地，永恒地，总是"},{"en":"invasion","zh":"n. 入侵, 侵略,侵犯"},{"en":"invent","zh":"v. 发明, 创造;捏造, 虚构"},{"en":"invention","zh":"n. 发明, 创造,发明物"},{"en":"inventory","zh":"n. 详细目录, 存货,财产清册, 总量"},{"en":"inverse","zh":"a. 相反的, 倒转的,反转的 n. 相反之物 v. 倒转"},{"en":"invert","zh":"v. 倒置, 倒转,颠倒"},{"en":"invest","zh":"vt.投资,投入( 精力、时间等)"},{"en":"investigate","zh":"v. 调查, 调查研究"},{"en":"investment","zh":"n. 投资, 投资额"},{"en":"invisible","zh":"a. 看不见的, 无形的"},{"en":"invitation","zh":"n. 邀请, 招待;请柬"},{"en":"invite","zh":"vt.邀请,招待"},{"en":"involve","zh":"v. 卷入, 陷入,连累; 包含,含有, 涉及"},{"en":"inward","zh":"ad.向内,在内 a. 向内的,在内的, 里面的"},{"en":"iron","zh":"n. 铁, 铁制品,烙铁, 熨斗 v. 熨( 衣), 熨平"},{"en":"irony","zh":"n. 反话, 讽刺, 讽刺之事"},{"en":"irrespective","zh":"a. 不顾的, 不考虑的,无关的"},{"en":"irrigate","zh":"vt.灌溉，修水利 vi.进行灌溉"},{"en":"irritate","zh":"vt.激怒,恼火, 使急躁"},{"en":"island","zh":"n. 岛，岛屿；( 道路上的)交通安全岛"},{"en":"isle","zh":"n. 小岛( 用于诗歌中)"},{"en":"isolate","zh":"vt.隔离,孤立"},{"en":"issue","zh":"n. 问题, 争端,发行( 物), 期号 vt.发行,流出"},{"en":"it","zh":"pron.它；[作无人称动词的主语]"},{"en":"item","zh":"n. 条( 款)，项目；一则( 新闻)，( 戏剧的)节目"},{"en":"its","zh":"pron.[it 的所有格]它的"},{"en":"itself","zh":"pron.(it 的反身代词)它自己，它本身"},{"en":"jacket","zh":"n. 短上衣, 茄克衫"},{"en":"jam","zh":"n. 阻塞, 轧住;果酱 v.(使) 阻塞,( 使)轧住不动"},{"en":"January","zh":"n. 一月"},{"en":"jar","zh":"n. 罐坛, 广口瓶"},{"en":"jargon","zh":"n. 行话"},{"en":"jaw","zh":"n. 颌, 颚"},{"en":"jazz","zh":"n. 爵士乐"},{"en":"jealous","zh":"a.(of)妒忌的; 猜疑的,警惕的"},{"en":"jeans","zh":"n. 牛仔裤（又称 blue jeans, dungarees 等）"},{"en":"jet","zh":"n. 喷气发动机, 喷气式飞机;喷口 v. 喷出,喷射"},{"en":"jewel","zh":"n. 宝石, 宝石饰物"},{"en":"jewelry","zh":"n.(jewllery)(总称)珠宝"},{"en":"job","zh":"n. 工作，职位；零活，一件工作；任务，职责"},{"en":"jog","zh":"v. 慢跑"},{"en":"join","zh":"v. 参加，加入；联合，连接；和…在一起"},{"en":"joint","zh":"n. 接合处, 接头;关节 a. 联合的,共同的, 连接的"},{"en":"joke","zh":"n. 笑话, 玩笑 v. 说笑话, 开玩笑"},{"en":"jolly","zh":"a. 欢乐的, 高兴的"},{"en":"journal","zh":"n. 定期刊物, 杂志,日报; 日志,日记"},{"en":"journalist","zh":"n. 记者, 新闻工作者"},{"en":"journey","zh":"n. 旅行, 旅程 v. 旅行"},{"en":"joy","zh":"n. 欢乐, 喜悦;乐事, 乐趣"},{"en":"judge","zh":"n. 法官; 裁判员;鉴定人 vt .审判; 评论,裁判"},{"en":"judgement","zh":"n.(judgment)审判, 判决;判断( 力); 看法,意见"},{"en":"judicial","zh":"a. 司法的，法庭的，审判的；明断的，公正的"},{"en":"jug","zh":"n.(有柄，小口，可盛水等的)大壶，罐，盂"},{"en":"juice","zh":"n.(水果等)汁, 液"},{"en":"July","zh":"n. 七月"},{"en":"jump","zh":"v./n.跳跃,跳动, 跳过;暴涨, 猛增"},{"en":"junction","zh":"n. 连接, 接合,交叉点, 枢纽站,接头, 中继线"},{"en":"June","zh":"n. 六月"},{"en":"jungle","zh":"n. 丛林, 生死地带"},{"en":"junior","zh":"a./n.年少的/者, 三年级的/学生, 下级(的)"},{"en":"junk","zh":"n. 废物，旧货；舢板"},{"en":"jury","zh":"n. 陪审团; 全体评审员"},{"en":"just","zh":"ad.正好地；刚才；只不过 a. 公正的，公平的"},{"en":"justice","zh":"n. 公正, 公平;审判, 司法"},{"en":"justify","zh":"v. 证明...正当(或有理、正确) ，为...辩护"},{"en":"juvenile","zh":"n. 青少年, 少年读物 a. 青少年的, 幼稚的"},{"en":"keen","zh":"a. 锋利的; 敏锐的;敏捷的;(on)热心的,渴望的"},{"en":"keep","zh":"v. 保持, 保存,遵守, 经营,看守, 拘留,维持"},{"en":"kettle","zh":"n. 水壶"},{"en":"key","zh":"n. 钥匙；答案；关键；键 a. 主要的，关键的"},{"en":"keyboard","zh":"n. 键盘 vt .用键盘输入( 信息)"},{"en":"kick","zh":"n./v.踢"},{"en":"kid","zh":"n. 小孩, 儿童 v. 戏弄, 取笑"},{"en":"kidnap","zh":"vt.诱拐；绑架，劫持"},{"en":"kidney","zh":"n. 肾, 肾脏"},{"en":"kill","zh":"vt.杀死，消灭；破坏，毁灭；消磨(时间)"},{"en":"kilo","zh":"n.(kilogram/kilogramme)千克"},{"en":"kilometre","zh":"n.(kilometer) 公里，千米( 略作 km)"},{"en":"kin","zh":"n. 家族, 亲属,血缘关系 a. 亲属关系的,同类的"},{"en":"kind","zh":"a. 仁慈的，友好的，亲切的，和蔼的 n. 种类"},{"en":"kindergarten","zh":"n. 幼儿园"},{"en":"kindness","zh":"n. 仁慈, 亲切;好意; 友好行为"},{"en":"king","zh":"n. 君主，国王"},{"en":"kingdom","zh":"n. 王国, 领域"},{"en":"kiss","zh":"n./v.吻,接吻"},{"en":"kit","zh":"n. 成套工具, 用具包,工具箱"},{"en":"kitchen","zh":"n. 厨房"},{"en":"kite","zh":"n. 风筝"},{"en":"knee","zh":"n. 膝, 膝盖"},{"en":"kneel","zh":"v. 跪, 下跪"},{"en":"knife","zh":"n. 刀, 餐刀 v. 用刀切, 用匕首刺"},{"en":"knit","zh":"v. 编织, 编结;接合, 粘合"},{"en":"knob","zh":"n. 门把,( 球形) 把手,旋纽"},{"en":"knock","zh":"v. 敲, 敲打,碰撞 n. 敲,击"},{"en":"knot","zh":"n.(绳)结;( 树) 节;节(= 海里/ 小时) v. 打结"},{"en":"know","zh":"vt.知道，了解；认识；识别 vi.知道，了解"},{"en":"knowledge","zh":"n. 知识, 学识;知道, 了解"},{"en":"lab","zh":"n.(laboratory)实验室"},{"en":"label","zh":"n. 标签 v. 把...称为；用标签于；用标签标明"},{"en":"labor","zh":"n.(labour)工作，劳动；劳力 v. 劳动，苦干"},{"en":"lace","zh":"n. 花边; 带子,鞋带 v. 系带,扎带"},{"en":"lack","zh":"n./v.缺乏,不足"},{"en":"lad","zh":"n. 男孩, 小伙子"},{"en":"ladder","zh":"n. 梯子, 阶梯"},{"en":"lady","zh":"n. 女士, 夫人"},{"en":"lag","zh":"v./n.落后,滞后 vt .用隔热材料覆盖( 锅炉等)"},{"en":"lake","zh":"n. 湖泊，湖水"},{"en":"lamb","zh":"n. 羔羊, 小羊;羔羊肉"},{"en":"lame","zh":"a. 跛的,( 辩解、论据等) 无说服力的"},{"en":"lamp","zh":"n. 灯"},{"en":"land","zh":"n. 陆地, 土地,国家 v.(使) 靠岸(登陆, 降落)"},{"en":"landlady","zh":"n. 女房东, 女地主"},{"en":"landlord","zh":"n. 房东, 地主"},{"en":"lane","zh":"n. 小路, 小巷,行车道"},{"en":"language","zh":"n. 语言, 术语,( 运用语言的)方式、风格"},{"en":"lantern","zh":"n. 灯, 灯笼"},{"en":"lap","zh":"n. 大腿,( 跑道的) 一圈,一段路程, 工作阶段"},{"en":"lapse","zh":"n. 失误, 流逝,丧失, 下降 v. 失效, 偏离,流逝"},{"en":"laptop","zh":"n. 膝上型电脑"},{"en":"large","zh":"a. 大的, 广大的,大规模的"},{"en":"largely","zh":"ad.主要地,基本上; 大量地,大规模地"},{"en":"laser","zh":"n. 激光"},{"en":"lash","zh":"v. 鞭打, 摆动,捆扎 n. 鞭子,鞭打, 睫毛,讽刺"},{"en":"last","zh":"a. 最后的，刚过去的 ad .最后 n. 最后 v. 持续"},{"en":"late","zh":"a. 迟的，晚的，晚期的；已故的 ad .迟，晚"},{"en":"lately","zh":"ad.最近,不久前"},{"en":"latent","zh":"a. 潜在的, 潜伏的,不易察觉的"},{"en":"later","zh":"ad.后来,过后"},{"en":"lateral","zh":"n. 侧面的, 旁边的"},{"en":"Latin","zh":"a. 拉丁的, 拉丁文的 n. 拉丁语"},{"en":"latitude","zh":"n. 纬度, 行动或言论的自由(范围),(pl.)地区"},{"en":"latter","zh":"a. 后者的；后一半的，接近终了的 n. 后者"},{"en":"laugh","zh":"v. 笑;(on)讥笑 n. 笑, 笑声"},{"en":"laughter","zh":"n. 笑, 笑声"},{"en":"launch","zh":"v. 发射; 使(船) 下水,发动, 开展 n. 发射, 下水"},{"en":"laundry","zh":"n. 洗衣房( 店); 待洗衣物,所洗衣物"},{"en":"lavatory","zh":"n. 厕所, 盥洗室"},{"en":"law","zh":"n. 法律, 法规,法学, 规律,定律"},{"en":"lawn","zh":"n. 草地, 草坪"},{"en":"lawyer","zh":"n. 律师"},{"en":"lay","zh":"v. 放，搁；下( 蛋)；铺设，敷设；设置，布置"},{"en":"layer","zh":"n. 层，层次；铺设者"},{"en":"layman","zh":"n. 外行"},{"en":"layoff","zh":"n. 临时解雇, 操作停止,活动停止期间, 失业期"},{"en":"layout","zh":"n. 安排，布局，设计；规划图，布局图"},{"en":"lazy","zh":"a. 懒惰的, 懒散的"},{"en":"lead","zh":"v. 领导; 领先;通向, 导致 n. 带领, 引导;铅"},{"en":"leadership","zh":"n. 领导"},{"en":"leading","zh":"a. 领导的, 指导的;第一位的; 最主要的"},{"en":"leaf","zh":"n. 叶子;( 书刊的) 一页,一张; 金属薄片"},{"en":"leaflet","zh":"n. 小叶, 嫩叶;传单, 活页"},{"en":"league","zh":"n. 同盟, 联盟;联合会, 社团"},{"en":"leak","zh":"v. 漏, 泄漏 n. 漏洞, 漏隙;泄漏, 漏出"},{"en":"lean","zh":"v. 倾斜, 屈身;倚, 靠,依赖 a. 瘦的,无脂肪的"},{"en":"leap","zh":"v. 跳, 跳跃 n. 跳跃, 飞跃"},{"en":"learn","zh":"v. 学习，学，学会；(of，about)听到，获悉"},{"en":"learned","zh":"a. 博学的, 有学问的"},{"en":"learning","zh":"n. 知识, 学问;学习"},{"en":"lease","zh":"vt.出租,租用 n. 租借,租期, 租赁物"},{"en":"least","zh":"a. 最小的; 最少的 ad.最小;最少"},{"en":"leather","zh":"n. 皮革, 皮革制品"},{"en":"leave","zh":"v. 离开; 留下,忘带; 让,听任; 交付 n. 许可; 假期"},{"en":"lecture","zh":"n./v.演讲,讲课"},{"en":"left","zh":"n. 左面，左方 a. 左边的，左面的；在左方的"},{"en":"leg","zh":"n. 腿，腿部；支柱；( 旅程的)一段，一站"},{"en":"legacy","zh":"n. 遗产，遗赠；先人( 或过去)留下的东西"},{"en":"legal","zh":"a. 法律的, 法定的;合法的, 正当的"},{"en":"legend","zh":"n. 传说, 传奇"},{"en":"legislation","zh":"n. 法律( 规)；立法，法律的制定( 或通过)"},{"en":"legitimate","zh":"a. 合法的；合理的，合乎逻辑的 vt .使合法"},{"en":"leisure","zh":"n. 空闲, 闲暇;悠闲, 安逸"},{"en":"lemon","zh":"n. 柠檬"},{"en":"lend","zh":"vt.借给,贷( 款)"},{"en":"length","zh":"n. 长, 长度;一段, 一节,程度, 范围"},{"en":"lens","zh":"n. 透镜, 镜头"},{"en":"less","zh":"a./ad.更少的( 地), 更小的(地)"},{"en":"lesson","zh":"n.(功)课；[pl.]课程；教训"},{"en":"lest","zh":"conj.惟恐,免得"},{"en":"let","zh":"v. 让，允许，听任；设，假设；出租，租给"},{"en":"letter","zh":"n. 信, 函件;字母, 文字"},{"en":"level","zh":"n. 水平，水准，等级 v. 弄平，铺平 a. 水平的"},{"en":"lever","zh":"n. 杆, 杠杆,手段, 途径,工具"},{"en":"levy","zh":"n. 征收, 征税,征兵 v. 征收,征集, 征用"},{"en":"liability","zh":"n. 责任, 义务;(pl.)债务"},{"en":"liable","zh":"a. 有...倾向的；可能遭受...的；有责任的"},{"en":"liberal","zh":"a. 慷慨的, 大方的;富足的; 自由的,思想开放的"},{"en":"liberate","zh":"vt.解放,释放"},{"en":"liberty","zh":"n. 自由，自由权；特权"},{"en":"librarian","zh":"n. 图书管理员"},{"en":"library","zh":"n. 图书馆; 藏书室;藏书, 丛书,文库"},{"en":"license","zh":"n.(licence)许可证,执照 v. 准许,认可"},{"en":"lick","zh":"vt.舔；(火焰或浪) 掠过；打败 n. 舔；少量"},{"en":"lid","zh":"n. 盖"},{"en":"lie","zh":"vi.躺，平放；处于；位于 v. 说谎 n. 谎话"},{"en":"life","zh":"n. 生命，生存；一生，寿命；生活；生物"},{"en":"lifetime","zh":"n. 一生, 终生"},{"en":"lift","zh":"v. 升起, 举起,消散 n. 电梯, 上升,免费搭车"},{"en":"light","zh":"n. 光；灯 v. 点燃；照亮 a. 轻( 快)；淡；明亮"},{"en":"lightning","zh":"n. 闪电 a. 闪电般的,快速的"},{"en":"like","zh":"v. 喜欢 prep.象；比如 a. 相象的 n. 象…一样"},{"en":"likelihood","zh":"n. 可能性"},{"en":"likely","zh":"a. 很可能的, 有希望的 ad.大概,多半"},{"en":"likewise","zh":"ad.同样地,照样地; 又,也, 而且"},{"en":"limb","zh":"n. 肢, 翼,大树枝"},{"en":"limit","zh":"n. 界限, 限度,范围 v.(to)限制,限定"},{"en":"limitation","zh":"n. 限制, 局限性"},{"en":"limited","zh":"a. 有限的, 被限制的"},{"en":"limp","zh":"a. 柔软的, 易曲的 v./n.蹒跚,跛行"},{"en":"line","zh":"n. 线; 路线,航线; 排;线路; 界线 v. 排队; 加衬"},{"en":"linear","zh":"a. 线的，直线的，线状的；长度的；线性的"},{"en":"linen","zh":"n. 亚麻布, 亚麻布制品"},{"en":"liner","zh":"n. 班机, 定期轮船,邮船"},{"en":"linger","zh":"v. 逗留, 徘徊,拖延, 留恋,浪费光阴, 苟延残喘"},{"en":"linguistic","zh":"a. 语言的，语言学的"},{"en":"link","zh":"v. 连接, 联系 n. 环节, 链环"},{"en":"lion","zh":"n. 狮子"},{"en":"lip","zh":"n. 嘴唇"},{"en":"liquid","zh":"n. 液体 a. 液体的,液态的"},{"en":"liquor","zh":"n. 酒；溶液，液剂"},{"en":"list","zh":"n. 表, 目录,名单 v. 把…编列成表,列入表内"},{"en":"listen","zh":"vi.倾听(与介词 to 并用，方可置宾语)"},{"en":"literacy","zh":"n. 有文化, 有教养,有读写能力"},{"en":"literally","zh":"ad.照字面意义,逐字地; 确实"},{"en":"literary","zh":"a. 文学上的, 文学的;精通文学的, 从事写作的"},{"en":"literature","zh":"n. 文学, 文学作品,文献, 图书资料,印刷品"},{"en":"litre","zh":"n.(liter)升；公升(容量单位)"},{"en":"litter","zh":"n. 垃圾,( 杂乱的) 废物 v. 使杂乱, 乱丢"},{"en":"little","zh":"a. 小，幼小；不多的 ad ./n.不多，几乎没有"},{"en":"live","zh":"v. 活着, 生活,居住 a. 活的,生动的, 直播的"},{"en":"lively","zh":"a. 活泼的, 活跃的;栩栩如生的, 真实的"},{"en":"liver","zh":"n. 肝, 肝脏"},{"en":"living","zh":"a. 活的, 有生命的,天然的, 逼真的 n. 生活,生计"},{"en":"living-room","zh":"n. 起居室"},{"en":"load","zh":"v. 装( 货), 装载 n. 装载( 量), 负荷(量);(一)担"},{"en":"loaf","zh":"n. 一个面包"},{"en":"loan","zh":"n. 贷款; 出借,借出 v. 借出"},{"en":"lobby","zh":"n. 门廊, 门厅,( 会议)休息厅"},{"en":"local","zh":"a. 地方的, 当地的;局部的"},{"en":"locality","zh":"n. 位置, 地点"},{"en":"locate","zh":"v. 查出, 探出,查找…地点, 使…坐落于,位于"},{"en":"location","zh":"n. 位置, 场所,定位, 测位"},{"en":"lock","zh":"n. 锁 v. 锁,锁上"},{"en":"locker","zh":"n. 更衣箱"},{"en":"locomotive","zh":"n. 机车, 火车头 a. 运动的, 移动的,运载的"},{"en":"lodge","zh":"v. 临时住宿, 寄宿,寄存, 容纳 n. 传达室,小旅馆"},{"en":"lofty","zh":"a. 崇高的，高尚的；高傲的；极高的"},{"en":"log","zh":"n. 原木, 圆木;航海日志"},{"en":"logic","zh":"n. 逻辑, 逻辑学"},{"en":"logical","zh":"a. 逻辑的, 符合逻辑的"},{"en":"lonely","zh":"a. 孤独的，寂寞的；荒凉的，人迹稀少的"},{"en":"long","zh":"a. 长的，长时间的，长期的 ad .长久，长期地"},{"en":"longitude","zh":"n. 经度"},{"en":"look","zh":"vi./n.看，注视 v. 好像，显得 n. 外表，脸色"},{"en":"loom","zh":"n. 织布机, 织机 v. 隐现,( 危险、忧虑等) 迫近"},{"en":"loop","zh":"n. 圈, 环"},{"en":"loose","zh":"a.(宽)松的；不精确的；自由的，散漫的"},{"en":"loosen","zh":"v. 解开, 放松"},{"en":"lord","zh":"n.(Lord)上帝, 主;主人, 长官,君主, 贵族"},{"en":"lorry","zh":"n. 卡车, 运货汽车"},{"en":"lose","zh":"v. 丢失, 迷路,输掉, 亏本,失败, 走慢,使沉湎于"},{"en":"loss","zh":"n. 丧失，遗失；损失，损耗，亏损；失败"},{"en":"lot","zh":"n. 许多，大量；签，抽签；命运；场地"},{"en":"lottery","zh":"n. 抽彩；碰运气的事，难于算计的事"},{"en":"loud","zh":"a. 大声的, 响亮的;吵闹的, 喧嚣的"},{"en":"loudspeaker","zh":"n. 扬声器, 扩音器"},{"en":"lounge","zh":"n. 休息室, 起居室,客厅"},{"en":"love","zh":"n. 爱，爱情，喜欢 vt .爱，热爱；爱好，喜欢"},{"en":"lovely","zh":"a. 可爱的, 好看的;令人愉快的, 美好的"},{"en":"lover","zh":"n. 爱好者;(pl.)情侣"},{"en":"low","zh":"a. 低，矮；低级的，下层的，卑贱的；低声的"},{"en":"lower","zh":"a. 较低的, 下级的,下游的 v. 降下,放低"},{"en":"loyal","zh":"a.(to)忠诚的, 忠贞的"},{"en":"loyalty","zh":"n. 忠诚, 忠心"},{"en":"lubricate  v. 润滑, 加润滑油,行贿, 收买",},{"en":"luck","zh":"n. 运气; 好运,侥幸"},{"en":"lucky","zh":"a. 幸运的, 侥幸的"},{"en":"luggage","zh":"n. 行李, 皮箱"},{"en":"lumber","zh":"n. 木材, 木料"},{"en":"lump","zh":"n. 团, 块 v.(使)成团,( 使) 成块"},{"en":"lunar","zh":"a. 月亮的"},{"en":"lunch","zh":"n. 午餐，( 美)便餐"},{"en":"lung","zh":"n. 肺"},{"en":"lure","zh":"n. 吸引力, 魅力,诱惑物 vt .引诱，吸引"},{"en":"luxury","zh":"n. 奢侈, 华贵;奢侈品 a. 奢华的,豪华的"},{"en":"machine","zh":"n. 机器, 机械 v. 用机器加工"},{"en":"machinery","zh":"n.(总称)机器, 机械"},{"en":"mad","zh":"a. 发疯的; 狂热的,着迷的; 恼火的,生气的"},{"en":"madame","zh":"n.(madam)夫人，太太，女士"},{"en":"magazine","zh":"n. 杂志, 期刊"},{"en":"magic","zh":"n. 魔术, 魔(魅) 力,巫术 a. 有魔力的,魔术的"},{"en":"magistrate","zh":"n. 地方行政官，地方法官，治安官"},{"en":"magnet","zh":"n. 磁体, 磁铁"},{"en":"magnetic","zh":"a. 磁的, 有磁性的;有吸引力的"},{"en":"magnificent","zh":"a. 华丽的, 高尚的,宏伟的"},{"en":"magnify","zh":"vt.放大,扩大, 夸大,夸张"},{"en":"magnitude","zh":"n. 大小, 数量;巨大, 广大"},{"en":"maid","zh":"n. 少女, 处女,女仆"},{"en":"maiden","zh":"n. 少女, 处女 a. 未婚的, 纯洁的,无经验的"},{"en":"mail","zh":"n. 邮件 v. 邮寄"},{"en":"main","zh":"a. 主要的, 总的 n. 总管道; 干线"},{"en":"mainland","zh":"n. 大陆, 本土"},{"en":"maintain","zh":"v. 维修, 保养,维持, 供养,坚持, 主张,支持"},{"en":"maintenance","zh":"n. 维修, 保养,维持, 保持,生活费用"},{"en":"majesty","zh":"n. 雄伟, 壮丽,庄严, 威严;最高权威, 王权"},{"en":"major","zh":"a. 主要的 n. 成年人,专业学生, 主修课程 v. 主修"},{"en":"majority","zh":"n. 多数, 大多数,成年, 法定年龄"},{"en":"make","zh":"n.(产品)来源，制法 vt .制造，做成，准备"},{"en":"male","zh":"n./a.男性(的), 雄性( 的)"},{"en":"malignant","zh":"a. 恶性的，致命的；恶意的，恶毒的"},{"en":"mammal","zh":"n. 哺乳动物"},{"en":"man","zh":"n.(pl.men)人；人类( 单数，不加冠词)；男人"},{"en":"manage","zh":"v. 经营, 管理,处理; 设法,对付; 操纵,运用"},{"en":"management","zh":"n. 经营, 管理;处理, 操纵;管理部门"},{"en":"manager","zh":"n. 经理, 管理人"},{"en":"maneuver","zh":"n.(manoeuvre)机动;运用, 操作; v. 机动"},{"en":"manifest","zh":"v. 表明, 证明,显示 a. 明白的,明了的"},{"en":"manipulate","zh":"vt.(熟练地) 使用，操作；(巧妙地) 处理"},{"en":"mankind","zh":"n. 人类"},{"en":"manner","zh":"n. 方式; 举止;(pl.)风度,礼貌; 规矩;风俗"},{"en":"manual","zh":"a. 手的, 手工做的,体力的 n. 手册,指南"},{"en":"manufacture","zh":"v. 制造, 加工 n. 制造, 制造业;产品"},{"en":"manuscript","zh":"n. 手稿, 原稿"},{"en":"many","zh":"a. 许多的，多的 pron.许多人或物，许多"},{"en":"map","zh":"n. 地图, 图 vt.在地图上标示出,绘制地图"},{"en":"marble","zh":"n. 大理石, 云石"},{"en":"march","zh":"v.(使)行军,( 使) 行进 n. 行军, 行程"},{"en":"March","zh":"n. 三月( 略作 Mar.)"},{"en":"margin","zh":"n. 页边空白; 边缘;余地; 幅度"},{"en":"marginal","zh":"a. 记在页边的, 旁注的;( 意识)边缘的"},{"en":"marine","zh":"a. 海的, 海生的;船舶的, 航海的"},{"en":"marital","zh":"a. 婚姻的, 夫妻之间的"},{"en":"mark","zh":"n. 痕迹; 记号;分数 v. 标记,打分, 使有特色"},{"en":"market","zh":"n. 集市, 市场;销路, 需求(量) v. 销售"},{"en":"marriage","zh":"n. 结婚, 婚姻;结婚仪式"},{"en":"married","zh":"a. 已婚的, 夫妇的;(to)与…结婚的"},{"en":"marry","zh":"v. 结婚, 嫁,娶"},{"en":"marvelous","zh":"a.(marvellous)惊人的, 奇迹般的,妙极的"},{"en":"Marxist","zh":"a. 马克思主义的 n. 马克思主义者"},{"en":"masculine","zh":"a. 男性的，似男性的；［语法］阳性的"},{"en":"mask","zh":"n. 面具, 面罩;假面具, 伪装 v. 掩饰,化装"},{"en":"mass","zh":"n. 大量, 众多;团, 块;(pl.)群众,民众; 质量"},{"en":"massacre","zh":"vt.残杀,集体屠杀 n. 残杀,大屠杀"},{"en":"massive","zh":"a. 大而重的, 厚实的,粗大的; 大规模的,大量的"},{"en":"master","zh":"n. 男主人; 师傅;硕士 v. 精通,控制 a. 主要的"},{"en":"masterpiece","zh":"n. 杰作, 名著"},{"en":"mat","zh":"n. 席子, 垫子"},{"en":"match","zh":"n. 火柴; 比赛,竞赛; 对手,配偶 v. 匹配,相称"},{"en":"mate","zh":"n. 伙伴, 同事,同伴, 配偶 v. 结伴,配对, 交配"},{"en":"material","zh":"n. 材料, 原料,资料 a. 物质的, 肉体的,实质性的"},{"en":"mathematical","zh":"a. 数学的；数学上的"},{"en":"maths","zh":"n.(mathematics/math)数学"},{"en":"matter","zh":"n. 物质, 物体;毛病, 麻烦;事情 v. 有关系,要紧"},{"en":"mature","zh":"a. 成熟的, 熟的;成年人的 v.(使) 成熟"},{"en":"maximum","zh":"n. 最大值, 极限 a. 最大的, 最高的"},{"en":"may","zh":"aux.v.可能，也许；可以，被允许；祝，愿"},{"en":"May","zh":"n. 五月"},{"en":"maybe","zh":"adv.可能；大概；也许"},{"en":"mayor","zh":"n. 市长"},{"en":"me","zh":"pron.[I 的宾格] 我"},{"en":"meadow","zh":"n. 草地, 牧场"},{"en":"meal","zh":"n. 膳食, 一餐"},{"en":"mean","zh":"v. 表示…的意思 a. 卑鄙的;平均的 n. 平均值"},{"en":"meaning","zh":"n. 意思, 意义,含义; 重要性,价值"},{"en":"means","zh":"n. 方法, 手段"},{"en":"meantime","zh":"n.(meanwhile)其间,其时 ad .同时, 当时"},{"en":"meanwhile","zh":"n. 其时，其间 ad .当时，与此同时"},{"en":"measure","zh":"v. 测量, 分派,权衡 n. 尺寸,量度器, 措施,办法"},{"en":"meat","zh":"n.(食用)肉类"},{"en":"mechanic","zh":"n. 技工, 机修工"},{"en":"mechanical","zh":"a. 机械的, 由机构制成的;机械似的, 呆板的"},{"en":"mechanism","zh":"n. 机械装置, 机构;机制"},{"en":"medal","zh":"n. 奖章, 勋章,纪念章"},{"en":"medical","zh":"a. 医学的，医疗的，医药的；内科的"},{"en":"medicine","zh":"n. 内服药, 医药;医术; 医学,内科学"},{"en":"medieval","zh":"a. 中世纪的, 中古(时代) 的,老式的, 原始的"},{"en":"meditate","zh":"v. 想, 考虑,( 尤指宗教上的)沉思, 冥想"},{"en":"meditation","zh":"n. 熟虑;( 尤指宗教的) 默想,沉思;(pl.)冥想录"},{"en":"medium","zh":"n.(pl.media)媒体, 方法,媒介, 介质 a. 中等的"},{"en":"meet","zh":"n. 会, 集会 v. 遇见; 会谈;迎接; 满足;符合"},{"en":"meeting","zh":"n. 会议, 集合,汇合, 会见,接见, 汇合点"},{"en":"melody","zh":"n. 旋律，曲调；悦耳的音乐"},{"en":"melon","zh":"n. 甜瓜"},{"en":"melt","zh":"v.(使)融化,( 使) 熔化"},{"en":"member","zh":"n. 成员, 会员"},{"en":"membership","zh":"n. 会员资格, 成员资格"},{"en":"memo","zh":"n.(memorandum)备忘录"},{"en":"memorial","zh":"a. 记忆的, 纪念的 n. 纪念物, 纪念碑,纪念馆"},{"en":"memory","zh":"n. 记忆, 记忆力;回忆; 存储(器)"},{"en":"menace","zh":"vt./n.有危险性的人( 或物)；威胁，威吓"},{"en":"mend","zh":"v. 修理, 缝补;改正, 改进"},{"en":"mental","zh":"a. 精神的, 思想的,心理的, 智力的,脑力的"},{"en":"mention","zh":"v./n.提及,说起"},{"en":"menu","zh":"n. 菜单"},{"en":"merchandise","zh":"n. 商品, 货物"},{"en":"merchant","zh":"n. 商人, 零售商"},{"en":"mercury","zh":"n. 水银, 汞"},{"en":"mercy","zh":"n. 仁慈, 怜悯,宽恕"},{"en":"mere","zh":"a. 纯粹的; 仅仅,只不过"},{"en":"merely","zh":"adv.仅仅，只不过"},{"en":"merge","zh":"v.(使)结合，( 使)合并，( 使)合为一体"},{"en":"merit","zh":"n. 优点, 价值,功绩 v. 值得,应得"},{"en":"merry","zh":"a. 欢乐的, 愉快的"},{"en":"mess","zh":"n. 混乱, 混杂,脏乱 v. 弄脏,弄乱, 搞糟"},{"en":"message","zh":"n. 消息, 信息,通讯, 启示,教训, 广告词,预言"},{"en":"messenger","zh":"n. 送信者, 使者,传令兵"}]}